{"uid": "10.1016/0009-2614(87)80452-9", "publisher": "Published by Elsevier B.V.", "type": "Journal", "title": "Computer simulation using a non-spherical reference potential for polar fluids", "year": "1987", "author": ["Given name: C.P. / Surname: Williams", "Given name: S. / Surname: Gupta", "Given name: E. / Surname: McLaughlin"], "keywords": [], "abstract": [{"sent": "A Barker\u2014Henderson type splitting of the intermolecular potential has been used to obtain a non-spherical reference potential for a perturbation theory of polar fluids.", "token_pos": [["A", 0, 1, "DT"], ["Barker", 2, 8, "NNP"], ["\u2014", 8, 9, "HYPH"], ["Henderson", 9, 18, "NNP"], ["type", 19, 23, "NN"], ["splitting", 24, 33, "NN"], ["of", 34, 36, "IN"], ["the", 37, 40, "DT"], ["intermolecular", 41, 55, "JJ"], ["potential", 56, 65, "NN"], ["has", 66, 69, "VBZ"], ["been", 70, 74, "VBN"], ["used", 75, 79, "VBN"], ["to", 80, 82, "TO"], ["obtain", 83, 89, "VB"], ["a", 90, 91, "DT"], ["non-spherical", 92, 105, "JJ"], ["reference", 106, 115, "NN"], ["potential", 116, 125, "NN"], ["for", 126, 129, "IN"], ["a", 130, 131, "DT"], ["perturbation", 132, 144, "NN"], ["theory", 145, 151, "NN"], ["of", 152, 154, "IN"], ["polar", 155, 160, "JJ"], ["fluids", 161, 167, "NNS"], [".", 167, 168, "."]], "chemical_entity": []}, {"sent": "Monte Carlo simulations of the non-spherical reference fluid have been performed to obtain directly the reference fluid Helmholtz free energy A\n0, and the first-order free-energy term A\n1.", "token_pos": [["Monte", 0, 5, "NNP"], ["Carlo", 6, 11, "NNP"], ["simulations", 12, 23, "NNS"], ["of", 24, 26, "IN"], ["the", 27, 30, "DT"], ["non-spherical", 31, 44, "JJ"], ["reference", 45, 54, "NN"], ["fluid", 55, 60, "NN"], ["have", 61, 65, "VBP"], ["been", 66, 70, "VBN"], ["performed", 71, 80, "VBN"], ["to", 81, 83, "TO"], ["obtain", 84, 90, "VB"], ["directly", 91, 99, "RB"], ["the", 100, 103, "DT"], ["reference", 104, 113, "NN"], ["fluid", 114, 119, "NN"], ["Helmholtz", 120, 129, "NNP"], ["free", 130, 134, "JJ"], ["energy", 135, 141, "NN"], ["A", 142, 143, "NN"], ["0", 144, 145, "CD"], [",", 145, 146, ","], ["and", 147, 150, "CC"], ["the", 151, 154, "DT"], ["first", 155, 160, "JJ"], ["-", 160, 161, "HYPH"], ["order", 161, 166, "NN"], ["free", 167, 171, "JJ"], ["-", 171, 172, "HYPH"], ["energy", 172, 178, "NN"], ["term", 179, 183, "NN"], ["A", 184, 185, "NN"], ["1", 186, 187, "CD"], [".", 187, 188, "."]], "chemical_entity": []}, {"sent": "Resulting first-order expansion predicts reasonably well thermodynamic properties for the case of dipolar Lennard-Jones fluids; however, serious deviations are noted for the case of quadrupolar Lennard-Jones fluids.", "token_pos": [["Resulting", 0, 9, "VBG"], ["first", 10, 15, "JJ"], ["-", 15, 16, "HYPH"], ["order", 16, 21, "NN"], ["expansion", 22, 31, "NN"], ["predicts", 32, 40, "VBZ"], ["reasonably", 41, 51, "RB"], ["well", 52, 56, "RB"], ["thermodynamic", 57, 70, "JJ"], ["properties", 71, 81, "NNS"], ["for", 82, 85, "IN"], ["the", 86, 89, "DT"], ["case", 90, 94, "NN"], ["of", 95, 97, "IN"], ["dipolar", 98, 105, "JJ"], ["Lennard", 106, 113, "NNP"], ["-", 113, 114, "HYPH"], ["Jones", 114, 119, "NNP"], ["fluids", 120, 126, "NNS"], [";", 126, 127, ":"], ["however", 128, 135, "RB"], [",", 135, 136, ","], ["serious", 137, 144, "JJ"], ["deviations", 145, 155, "NNS"], ["are", 156, 159, "VBP"], ["noted", 160, 165, "VBN"], ["for", 166, 169, "IN"], ["the", 170, 173, "DT"], ["case", 174, 178, "NN"], ["of", 179, 181, "IN"], ["quadrupolar", 182, 193, "JJ"], ["Lennard", 194, 201, "NNP"], ["-", 201, 202, "HYPH"], ["Jones", 202, 207, "NNP"], ["fluids", 208, 214, "NNS"], [".", 214, 215, "."]], "chemical_entity": []}], "body_text": [], "figure_caption": [], "xas_info": []}